{
    "About": {
        "template": null,
        "content": "../content/about.md",
        "pathout": "../../Web/pages/about.html"
    },
    "Criteria": {
        "template": null,
        "content": "../../../Criteria/library_criteria.md",
        "pathout": "../../Web/pages/criteria.html"
    },
    "Contribute a Model": {
        "template": null,
        "content": "../content/contributemodel.md",
        "pathout": "../../Web/pages/contribute-a-model.html"
    },
    "Contribute to PSL": {
        "template": null,
        "content": "../../../Community/contribute.md",
        "pathout": "../../Web/pages/contribute.html"
    }
}